{"url": "https://www.mediapool.bg/tsvetanov-s-voenniya-si-mantalitet-prezidentat-ne-zachita-pravoviya-red-news282744.html", "text": "Вход в Mediapool.bgEmail:Парола:Вход в Mediapool.bgEmail:Парола:Вход в Mediapool.bgEmail:Парола:", "date": "2018.08.14", "title": "Цветанов: С военния си манталитет президентът не зачита правовия ред"}
{"url": "https://www.mediapool.bg/litva-prie-nova-natsionalna-strategiya-za-kibersigurnost-news282719.html", "text": "Вход в Mediapool.bgEmail:Парола:Вход в Mediapool.bgEmail:Парола:Вход в Mediapool.bgEmail:Парола:", "date": "2018.08.14", "title": "Литва прие нова национална стратегия за киберсигурност"}
{"url": "https://www.mediapool.bg/sreshtata-na-varha-mezhdu-dvete-korei-shte-se-sastoi-na-12-ili-13-septemvri-news282720.html", "text": "Вход в Mediapool.bgEmail:Парола:Вход в Mediapool.bgEmail:Парола:Вход в Mediapool.bgEmail:Парола:", "date": "2018.08.14", "title": "Срещата на върха между двете Кореи ще се състои на 12 или 13 септември"}
{"url": "https://www.mediapool.bg/sasht-vnimatelno-sledyat-finansovata-situatsiya-v-turtsiya-news282718.html", "text": "Вход в Mediapool.bgEmail:Парола:Вход в Mediapool.bgEmail:Парола:Вход в Mediapool.bgEmail:Парола:", "date": "2018.08.14", "title": "САЩ внимателно следят финансовата ситуация в Турция"}
{"url": "https://www.mediapool.bg/migrantskite-pototsi-kam-evropa-belezhat-ryazak-spad-prez-parvite-7-mesetsa-na-godinata-news282715.html", "text": "Вход в Mediapool.bgEmail:Парола:Вход в Mediapool.bgEmail:Парола:Вход в Mediapool.bgEmail:Парола:", "date": "2018.08.14", "title": "Мигрантските потоци към Европа бележат рязък спад през първите 7 месеца на годината"}
{"url": "https://www.mediapool.bg/neizvestni-podpaliha-80-koli-v-zapadna-shvetsiya-news282713.html", "text": "Вход в Mediapool.bgEmail:Парола:Вход в Mediapool.bgEmail:Парола:Вход в Mediapool.bgEmail:Парола:", "date": "2018.08.14", "title": "Неизвестни подпалиха 80 коли в Западна Швеция"}
{"url": "https://www.mediapool.bg/sofiya-shte-podlozhi-na-obsazhdane-chasten-proekt-za-kapalnyata-mariya-luiza-news282717.html", "text": "Вход в Mediapool.bgEmail:Парола:Вход в Mediapool.bgEmail:Парола:Вход в Mediapool.bgEmail:Парола:", "date": "2018.08.14", "title": "София ще подложи на обсъждане частен проект за къпалнята \"Мария Луиза\""}
{"url": "https://www.mediapool.bg/tsik-obzhalva-reshenieto-na-sada-za-zadalzhitelnoto-mashinno-glasuvane-news282716.html", "text": "Вход в Mediapool.bgEmail:Парола:Вход в Mediapool.bgEmail:Парола:Вход в Mediapool.bgEmail:Парола:Mediapool.Комисията е взела решение да обжалва и допустимостта на жалбата срещу нея. Причината е, чеMediapool разговоря, най-разумният вариант е Народното събрание да промени Изборния кодекс. \"Тогава дори и да осъдят ЦИК – решението няма да е кой знае какво, защото комисиятаMediapool (),", "date": "2018.08.14", "title": "ЦИК обжалва решението на съда за задължителното машинно гласуване"}
{"url": "https://www.mediapool.bg/polski-ministar-nareche-uchastnitsite-v-gei-parad-sodomiti-news282721.html", "text": "Вход в Mediapool.bgEmail:Парола:Вход в Mediapool.bgEmail:Парола:Вход в Mediapool.bgEmail:Парола:", "date": "2018.08.14", "title": "Полски министър нарече участниците в гей парад \"содомити\""}
{"url": "https://www.mediapool.bg/pozharnikar-e-12-tata-zhertva-na-pozharite-v-kaliforniya-news282722.html", "text": "Вход в Mediapool.bgEmail:Парола:Вход в Mediapool.bgEmail:Парола:Вход в Mediapool.bgEmail:Парола:", "date": "2018.08.14", "title": "Пожарникар е 12-тата жертва на пожарите в Калифорния"}
{"url": "https://www.mediapool.bg/bivsha-savetnichka-na-tramp-taino-zapisvala-razgovori-v-beliya-dom-news282712.html", "text": "Вход в Mediapool.bgEmail:Парола:Вход в Mediapool.bgEmail:Парола:Вход в Mediapool.bgEmail:Парола:", "date": "2018.08.14", "title": "Бивша съветничка на Тръмп тайно записвала разговори в Белия дом"}
{"url": "https://www.mediapool.bg/netanyahu-se-e-sreshtnal-s-egipetskiya-prezident-za-pregovori-za-ivitsata-gaza-news282714.html", "text": "Вход в Mediapool.bgEmail:Парола:Вход в Mediapool.bgEmail:Парола:Вход в Mediapool.bgEmail:Парола:", "date": "2018.08.14", "title": "Нетаняху се е срещнал с египетския президент за преговори за ивицата Газа"}
{"url": "https://www.mediapool.bg/talibanite-prevzeha-voenna-baza-v-severen-afganistan-news282723.html", "text": "Вход в Mediapool.bgEmail:Парола:Вход в Mediapool.bgEmail:Парола:Вход в Mediapool.bgEmail:Парола:", "date": "2018.08.14", "title": "Талибаните превзеха военна база в Северен Афганистан"}
{"url": "https://www.mediapool.bg/pazarite-se-gotvyat-za-sriv-na-britanskata-lira-zaradi-brekzit-news282726.html", "text": "Вход в Mediapool.bgEmail:Парола:Вход в Mediapool.bgEmail:Парола:Вход в Mediapool.bgEmail:Парола:", "date": "2018.08.14", "title": "Пазарите се готвят за срив на британската лира заради Брекзит"}
{"url": "https://www.mediapool.bg/dete-namereno-zaroveno-v-pustinyata-v-nyu-meksiko-e-bilo-ritualno-ubito-news282724.html", "text": "Вход в Mediapool.bgEmail:Парола:Вход в Mediapool.bgEmail:Парола:Вход в Mediapool.bgEmail:Парола:", "date": "2018.08.14", "title": "Дете, намерено заровено в пустинята в Ню Мексико, е било ритуално убито"}
{"url": "https://www.mediapool.bg/zhivotat-poskapna-prez-yuli-s-07-news282727.html", "text": "Вход в Mediapool.bgEmail:Парола:Вход в Mediapool.bgEmail:Парола:Вход в Mediapool.bgEmail:Парола:", "date": "2018.08.14", "title": "Животът поскъпна през юли с 0.7%"}
{"url": "https://www.mediapool.bg/zlatnite-pyana-kokteili-i-bira-po-dve-evro-news282697.html", "text": "Вход в Mediapool.bgEmail:Парола:Вход в Mediapool.bgEmail:Парола:Вход в Mediapool.bgEmail:Парола:", "date": "2018.08.14", "title": "\"Златните\": пяна, коктейли и бира по две евро"}
{"url": "https://www.mediapool.bg/ne-e-li-vreme-da-se-spre-sasipvaneto-na-sedemte-rilski-ezera-i-ne-samo-na-tyah-news282696.html", "text": "Вход в Mediapool.bgEmail:Парола:Вход в Mediapool.bgEmail:Парола:Вход в Mediapool.bgEmail:Парола:", "date": "2018.08.14", "title": "Не е ли време да се спре съсипването на Седемте Рилски езера – и не само на тях"}
{"url": "https://www.mediapool.bg/kristalina-georgieva-tsenite-nyama-da-se-vdignat-mnogo-sled-vlizaneto-v-evrozonata-news282699.html", "text": "Вход в Mediapool.bgEmail:Парола:Вход в Mediapool.bgEmail:Парола:Вход в Mediapool.bgEmail:Парола:", "date": "2018.08.14", "title": "Кристалина Георгиева: Цените няма да се вдигнат много след влизането в еврозоната"}
{"url": "https://www.mediapool.bg/svarzaniyat-s-mityo-ochite-obshtinar-bencho-benchev-veche-e-s-dve-obvineniya-news282702.html", "text": "Вход в Mediapool.bgEmail:Парола:Вход в Mediapool.bgEmail:Парола:Вход в Mediapool.bgEmail:Парола:", "date": "2018.08.14", "title": "Свързаният с Митьо Очите общинар Бенчо Бенчев вече е с две обвинения"}
{"url": "https://www.mediapool.bg/rekorden-byudzhet-za-pentagona-ot-716-mlrd-dolara-news282700.html", "text": "Вход в Mediapool.bgEmail:Парола:Вход в Mediapool.bgEmail:Парола:Вход в Mediapool.bgEmail:Парола:", "date": "2018.08.14", "title": "Рекорден бюджет за Пентагона от 716 млрд. долара"}
{"url": "https://www.mediapool.bg/srivat-na-turskata-lira-razpalva-strahove-ot-nova-finansova-kriza-news282703.html", "text": "Вход в Mediapool.bgEmail:Парола:Вход в Mediapool.bgEmail:Парола:Вход в Mediapool.bgEmail:Парола:", "date": "2018.08.14", "title": "Сривът на турската лира разпалва страхове от нова финансова криза"}
{"url": "https://www.mediapool.bg/dzhip-blasna-8-godishno-momche-vav-varna-news282701.html", "text": "Вход в Mediapool.bgEmail:Парола:Вход в Mediapool.bgEmail:Парола:Вход в Mediapool.bgEmail:Парола:", "date": "2018.08.14", "title": "Джип блъсна 8-годишно момче във Варна"}
{"url": "https://www.mediapool.bg/problemite-v-targovskiya-registar-shte-zatrudnyat-notarialnite-sdelki-news282705.html", "text": "Вход в Mediapool.bgEmail:Парола:Вход в Mediapool.bgEmail:Парола:Вход в Mediapool.bgEmail:Парола:През последните две години 8 левасайта \"Биволъ\" счетоводителят на Веселка Велчева обяснява, че тя няма нищо общо с надграждането на регистъра, а е взела 2300 лв за изработване на рекламни материали.Z", "date": "2018.08.14", "title": "Проблемите в Търговския регистър ще затруднят нотариалните сделки"}
{"url": "https://www.mediapool.bg/ministarat-na-obrazovanieto-otnovo-obeshta-zaplata-ot-1300-lv-za-uchitelite-ot-2019-g-news282706.html", "text": "Вход в Mediapool.bgEmail:Парола:Вход в Mediapool.bgEmail:Парола:Вход в Mediapool.bgEmail:Парола:", "date": "2018.08.14", "title": "Министърът на образованието отново обеща заплата от 1300 лв. за учителите от 2019 г."}
{"url": "https://www.mediapool.bg/rozoproizvoditelite-poluchiha-blizo-2-mln-leva-darzhavna-pomosht-news282707.html", "text": "Вход в Mediapool.bgEmail:Парола:Вход в Mediapool.bgEmail:Парола:Вход в Mediapool.bgEmail:Парола:", "date": "2018.08.14", "title": "Розопроизводителите получиха близо 2 млн. лева държавна помощ"}
{"url": "https://www.mediapool.bg/shte-se-pregovarya-s-dve-firmi-za-iztochvane-na-gorivoto-ot-potanaliya-korab-krai-sozopol-news282708.html", "text": "Вход в Mediapool.bgEmail:Парола:Вход в Mediapool.bgEmail:Парола:Вход в Mediapool.bgEmail:Парола:", "date": "2018.08.14", "title": "Ще се преговаря с две фирми за източване на горивото от потъналия кораб край Созопол"}
{"url": "https://www.mediapool.bg/nad-280-kg-negodni-hrani-sa-izzeti-ot-morski-hoteli-i-zavedeniya-news282709.html", "text": "Вход в Mediapool.bgEmail:Парола:Вход в Mediapool.bgEmail:Парола:Вход в Mediapool.bgEmail:Парола:", "date": "2018.08.14", "title": "Над 280 кг негодни храни са иззети от морски хотели и заведения"}
{"url": "https://www.mediapool.bg/novo-teroristichno-napadenie-v-london-kola-se-vryaza-v-ograzhdeniyata-do-parlamenta-v-london-news282704.html", "text": "Вход в Mediapool.bgEmail:Парола:Вход в Mediapool.bgEmail:Парола:Вход в Mediapool.bgEmail:Парола:", "date": "2018.08.14", "title": "Ново терористично нападение в Лондон: кола се вряза в огражденията до парламента в Лондон"}
{"url": "https://www.mediapool.bg/zaev-prizova-da-izvadim-goliya-populizam-ot-otnosheniyata-sofiya-skopie-news282710.html", "text": "Вход в Mediapool.bgEmail:Парола:Вход в Mediapool.bgEmail:Парола:Вход в Mediapool.bgEmail:Парола:", "date": "2018.08.14", "title": "Заев призова: Да извадим \"голия популизъм\" от  отношенията София-Скопие"}
{"url": "https://www.mediapool.bg/lyatna-politicheska-butaforiya-news282711.html", "text": "Вход в Mediapool.bgEmail:Парола:Вход в Mediapool.bgEmail:Парола:Вход в Mediapool.bgEmail:Парола:", "date": "2018.08.14", "title": "Лятна политическа бутафория"}
{"url": "https://www.mediapool.bg/apokaliptichno-desetki-zhertvi-na-srutil-se-most-krai-genua-news282728.html", "text": "Вход в Mediapool.bgEmail:Парола:Вход в Mediapool.bgEmail:Парола:Вход в Mediapool.bgEmail:Парола:", "date": "2018.08.14", "title": "Апокалиптично: Десетки жертви на срутил се мост край Генуа"}
{"url": "https://www.mediapool.bg/lekarite-i-patsientite-sa-po-aktivni-v-saobshtavaneto-na-nezhelani-reaktsii-ot-lekarstva-news282725.html", "text": "Вход в Mediapool.bgEmail:Парола:Вход в Mediapool.bgEmail:Парола:Вход в Mediapool.bgEmail:Парола:", "date": "2018.08.14", "title": "Лекарите и пациентите са по-активни в съобщаването на нежелани реакции от лекарства"}
{"url": "https://www.mediapool.bg/da-bulgaria-premierat-da-poeme-otgovornost-za-krizata-v-agentsiyata-po-vpisvaniyata-news282729.html", "text": "Вход в Mediapool.bgEmail:Парола:Вход в Mediapool.bgEmail:Парола:Вход в Mediapool.bgEmail:Парола:", "date": "2018.08.14", "title": "\"Да, България\": Премиерът да поеме отговорност за кризата в Агенцията по вписванията"}
{"url": "https://www.mediapool.bg/iziskvaniyata-kam-rodilnite-otdeleniya-se-zanizhavat-zaradi-bolnitsata-v-karlovo-news282736.html", "text": "Вход в Mediapool.bgEmail:Парола:Вход в Mediapool.bgEmail:Парола:Вход в Mediapool.bgEmail:Парола:", "date": "2018.08.14", "title": "Изискванията към родилните отделения се занижават заради болницата в Карлово"}
{"url": "https://www.mediapool.bg/krai-na-primirieto-siderov-v-nov-gneven-izblik-sreshtu-simeonov-news282732.html", "text": "Вход в Mediapool.bgEmail:Парола:Вход в Mediapool.bgEmail:Парола:Вход в Mediapool.bgEmail:Парола:(Какао бийч)", "date": "2018.08.14", "title": "Край на примирието: Сидеров в нов гневен изблик срещу Симеонов"}
{"url": "https://www.mediapool.bg/gazovata-vrazka-s-gartsiya-e-osvobodena-ot-tarifna-regulatsiya-news282733.html", "text": "Вход в Mediapool.bgEmail:Парола:Вход в Mediapool.bgEmail:Парола:Вход в Mediapool.bgEmail:Парола:", "date": "2018.08.14", "title": "Газовата връзка с Гърция е освободена от тарифна регулация"}
{"url": "https://www.mediapool.bg/mazh-zapali-semeinata-si-kashta-v-omurtag-sled-imoten-spor-sas-sestra-si-news282734.html", "text": "Вход в Mediapool.bgEmail:Парола:Вход в Mediapool.bgEmail:Парола:Вход в Mediapool.bgEmail:Парола:", "date": "2018.08.14", "title": "Мъж запали семейната си къща в Омуртаг след имотен спор със сестра си"}
{"url": "https://www.mediapool.bg/vivakom-s-rast-na-prihodi-i-pechalba-za-shestmesechieto-news282735.html", "text": "Вход в Mediapool.bgEmail:Парола:Вход в Mediapool.bgEmail:Парола:Вход в Mediapool.bgEmail:Парола:", "date": "2018.08.14", "title": "\"Виваком\" с ръст на приходи и печалба за шестмесечието"}
{"url": "https://www.mediapool.bg/hilyadi-koli-ostavat-bez-grazhdanska-otgovornost-ot-petak-news282730.html", "text": "Вход в Mediapool.bgEmail:Парола:Вход в Mediapool.bgEmail:Парола:Вход в Mediapool.bgEmail:Парола:", "date": "2018.08.14", "title": "Хиляди коли остават без \"Гражданска отговорност\" от петък"}
{"url": "https://www.mediapool.bg/kataluniya-obyavi-gotovnost-da-prieme-koraba-akuarius-sas-141-migranti-na-borda-news282737.html", "text": "Вход в Mediapool.bgEmail:Парола:Вход в Mediapool.bgEmail:Парола:Вход в Mediapool.bgEmail:Парола:", "date": "2018.08.14", "title": "Каталуния обяви готовност да приеме кораба \"Акуариус\" със 141 мигранти на борда"}
{"url": "https://www.mediapool.bg/orban-neutralizira-zaplahata-ot-mediynata-imperiya-na-bivsh-priyatel-prevarnal-se-vav-vrag-news282738.html", "text": "Вход в Mediapool.bgEmail:Парола:Вход в Mediapool.bgEmail:Парола:Вход в Mediapool.bgEmail:Парола:", "date": "2018.08.14", "title": "Орбан неутрализира заплахата от медийната империя на бивш приятел, превърнал се във враг"}
{"url": "https://www.mediapool.bg/novi-161-dushi-s-hiv-ot-nachaloto-na-godinata-news282739.html", "text": "Вход в Mediapool.bgEmail:Парола:Вход в Mediapool.bgEmail:Парола:Вход в Mediapool.bgEmail:Парола:", "date": "2018.08.14", "title": "Нови 161 души с ХИВ от началото на годината"}
{"url": "https://www.mediapool.bg/lavrov-dnite-na-dolara-kato-globalna-valuta-sa-prebroeni-news282740.html", "text": "Вход в Mediapool.bgEmail:Парола:Вход в Mediapool.bgEmail:Парола:Вход в Mediapool.bgEmail:Парола:", "date": "2018.08.14", "title": "Лавров: Дните на долара като глобална валута са преброени"}
{"url": "https://www.mediapool.bg/prokuraturata-shte-proveri-sluchaya-s-horoto-v-edno-ot-rilskite-ezera-news282741.html", "text": "Вход в Mediapool.bgEmail:Парола:Вход в Mediapool.bgEmail:Парола:Вход в Mediapool.bgEmail:Парола:", "date": "2018.08.14", "title": "Прокуратурата ще провери случая с хорото в едно от Рилските езера"}
{"url": "https://www.mediapool.bg/turskiyat-biznes-prizova-erdogan-da-reshi-spora-sas-sasht-news282731.html", "text": "Вход в Mediapool.bgEmail:Парола:Вход в Mediapool.bgEmail:Парола:Вход в Mediapool.bgEmail:Парола:() и Съюзът на камарите и стоковите борси на Турция заяви, че \"за да бъдат стабилизирани валутните курсове, е нужно затягане на монетарната политика\".", "date": "2018.08.14", "title": "Турският бизнес призова Ердоган да реши спора със САЩ"}
{"url": "https://www.mediapool.bg/osse-otkri-moderni-ruski-orazhiya-v-separatistkite-raioni-na-ukraina-news282742.html", "text": "Вход в Mediapool.bgEmail:Парола:Вход в Mediapool.bgEmail:Парола:Вход в Mediapool.bgEmail:Парола:И", "date": "2018.08.14", "title": "ОССЕ откри модерни руски оръжия в сепаратистките райони на Украйна"}
